comptSort/__about__.py
comptSort/__init__.py
comptSort/cli.py
comptSort/comptSort.py
comptSort/py.typed
comptSort/algorithms/__init__.py
comptSort/algorithms/algorithms.py
comptSort/algorithms/binary_insertion.py
comptSort/algorithms/binary_search.py
comptSort/algorithms/bubble.py
comptSort/algorithms/insertion.py
comptSort/algorithms/merge.py
comptSort/algorithms/quick.py
comptSort/algorithms/sorter.py
comptSort-0.3.0.dist-info/LICENSE
comptSort-0.3.0.dist-info/METADATA
comptSort-0.3.0.dist-info/WHEEL
comptSort-0.3.0.dist-info/entry_points.txt
comptSort-0.3.0.dist-info/top_level.txt
comptSort-0.3.0.dist-info/RECORD
