Metadata-Version: 2.1
Name: comptSort
Version: 0.3.0
Summary: Sorting function.
Home-page: https://github.com/jacobszpz/comptSort
Author: Jacob Sánchez
Author-email: jacobszpz@protonmail.com
License: GNU General Public License v2
Project-URL: Source, https://github.com/jacobszpz/comptSort
Keywords: sorting
Classifier: Development Status :: 4 - Beta
Classifier: License :: OSI Approved :: GNU General Public License v2 (GPLv2)
Classifier: Programming Language :: Python :: 3.9
Classifier: Programming Language :: Python :: 3.10
Classifier: Intended Audience :: Developers
Requires-Python: >=3.9
License-File: LICENSE
